{
  "kind": "collectionType",
  "collectionName": "branches",
  "info": {
    "singularName": "branch",
    "pluralName": "branches",
    "displayName": "branch"
  },
  "options": {
    "draftAndPublish": true
  },
  "pluginOptions": {},
  "attributes": {
    "name": {
      "type": "string"
    },
    "authors": {
      "type": "relation",
      "relation": "oneToMany",
      "target": "api::author.author",
      "mappedBy": "branch"
    },
    "users": {
      "type": "relation",
      "relation": "oneToMany",
      "target": "plugin::users-permissions.user",
      "mappedBy": "branch"
    }
  }
}
